rmidi/MIDI.py
rmidi/__init__.py
rmidi/absolutemidi.py
rmidi/analyser.py
rmidi/mutils.py
rmidi/rmidix.py
rmidi/sequencer.py
rmidi/sound.py
rmidi/constant/Constants.py
rmidi/constant/__init__.py
rmidi/constant/ch_event_format.py
rmidi/constant/converter.py
rmidi/constant/event_format.py
rmidi/constant/meta_event_format.py
rmidi/constant/sys_event_format.py
rmidi/dataset/__init__.py
rmidi/dataset/config.py
rmidi/dataset/piano_roll.py
rmidi/dataset/reader.py
rmidi-0.0.29.dist-info/LICENSE
rmidi-0.0.29.dist-info/METADATA
rmidi-0.0.29.dist-info/WHEEL
rmidi-0.0.29.dist-info/top_level.txt
rmidi-0.0.29.dist-info/RECORD
