Metadata-Version: 2.1
Name: rmidi
Version: 0.0.29
Summary: Math Sequence to MIDI
Home-page: https://github.com/rushike/rmidipy
Author: rushike
Author-email: rushike.ab1@gmail.com
License: UNKNOWN
Platform: UNKNOWN
Classifier: Programming Language :: Python :: 3
Classifier: License :: OSI Approved :: MIT License
Classifier: Operating System :: OS Independent
Requires-Dist: numpy
